mint/__init__.py
mint/__main__.py
mint/_version.py
mint/mydatasources.cfg
mint/version.py
mint/app/__init__.py
mint/app/createApp.py
mint/app/dirs.py
mint/app/entryPoint.py
mint/data/__init__.py
mint/data/blueprint.json
mint/data/csv_to_semicolon_separator.py
mint/data/mint.schema.json
mint/data/canvas_properties/default_properties.json
mint/data/data_signals/DataExport_20231222.csv
mint/data/scsv/IDV246.scsv
mint/data/workspaces/CustomizedPulsesPlots.json
mint/data/workspaces/CustomizedPulsesPlotsWithStartEnd.json
mint/data/workspaces/DifiTest.json
mint/data/workspaces/ExampleOfComplexLayout.json
mint/data/workspaces/IDV246.json
mint/data/workspaces/IDV249.json
mint/data/workspaces/IDV253.json
mint/data/workspaces/IDV280.json
mint/data/workspaces/IDV346.json
mint/data/workspaces/OverlayPulsesID.json
mint/data/workspaces/WeekComparison.json
mint/data/workspaces/WeekComparisonSamePlot.json
mint/data/workspaces/XAndYcolumns.json
mint/data/workspaces/largeCanvas100.json
mint/data/workspaces/mycommissioningTest.json
mint/data/workspaces/proc_example_inp_2.json
mint/gui/__init__.py
mint/gui/mtAbout.py
mint/gui/mtDataRangeSelector.py
mint/gui/mtExportConfigurator.py
mint/gui/mtFindReplace.py
mint/gui/mtMainWindow.py
mint/gui/mtMemoryMonitor.py
mint/gui/mtSignalConfigurator.py
mint/gui/mtSignalToolBar.py
mint/gui/mtStatusBar.py
mint/gui/mtStreamConfigurator.py
mint/gui/compiled/__init__.py
mint/gui/compiled/uiExportConfig.py
mint/gui/compiled/uiStreamerConfig.py
mint/gui/icons/append_file.png
mint/gui/icons/error.png
mint/gui/icons/fullscreen.png
mint/gui/icons/mint.drawio
mint/gui/icons/mint128x128.png
mint/gui/icons/mint16x16.png
mint/gui/icons/mint256x256.png
mint/gui/icons/mint32x32.png
mint/gui/icons/mint64x64.png
mint/gui/icons/nofullscreen.png
mint/gui/icons/open.png
mint/gui/icons/open_file.png
mint/gui/icons/options.png
mint/gui/icons/plot.png
mint/gui/icons/redo.png
mint/gui/icons/rotate180.png
mint/gui/icons/save_as.png
mint/gui/icons/size.png
iter_mint-1.3.1.post1.dist-info/METADATA
iter_mint-1.3.1.post1.dist-info/WHEEL
iter_mint-1.3.1.post1.dist-info/entry_points.txt
iter_mint-1.3.1.post1.dist-info/top_level.txt
iter_mint-1.3.1.post1.dist-info/RECORD
