Metadata-Version: 2.4
Name: iter-mint
Version: 1.3.1.post1
Summary: A Python Qt application for ITER Data Visualtization using the iplotlib framework
Author-email: ITER Organization <jscabanilla@minsait.com>
Maintainer-email: Jhon Steeven Cabanilla Alvarado <jscabanilla@minsait.com>, Pablo Martin Villares <pmartin@minsait.com>, Mario Gomez Ballesteros <mgomezb@minsait.com>
License: MIT
Project-URL: Homepage, https://github.com/iplot-viz/mint
Project-URL: Repository, https://github.com/iplot-viz/mint.git
Project-URL: Issues, https://github.com/iplot-viz/mint/issues
Keywords: MINT,Qt,Application,UDA,Data,Visualization
Classifier: Programming Language :: Python :: 3
Classifier: License :: OSI Approved :: MIT License
Classifier: Operating System :: OS Independent
Requires-Python: >=3.9
Requires-Dist: iplotLogging>=1.2.0
Requires-Dist: iplotlib>=1.3.2
Requires-Dist: iplotDataAccess>=1.3.1
Requires-Dist: iplotWidgets>=1.3.0
Requires-Dist: iplotProcessing>=1.1.5
Requires-Dist: psutil>=5.8.0
Provides-Extra: test
Requires-Dist: pytest>=6.0; extra == "test"
